Workbook

Sheet Cover
A1: APPLE INC. (AAPL)
A2: 3-Statement Financial Model | Investment Banking Format
A4: Model Version: | B4: v1.0
A5: Last Updated: | B5: =TODAY() -> 46095
A6: Prepared By: | B6: Financial Analyst
A7: Base Currency: | B7: USD
A8: Units: | B8: USD Millions ($M)
A9: Fiscal Year End: | B9: September
A10: Projection Period: | B10: FY2024A – FY2026E (3 Actuals + 2 Forecast)
A11: Data Source: | B11: Apple Inc. SEC 10-K Filings
A13: 📋 MODEL STRUCTURE
A14: Assumptions | B14: All revenue/cost/balance sheet drivers — ONLY edit blue cells here
A15: Revenue | B15: Revenue build from real Apple product segment data
A16: Costs | B16: COGS schedule and operating expense build
A17: Depreciation | B17: PP&E roll-forward and D&A schedule
A18: Working Capital | B18: AR / Inventory / AP days-based WC schedule
A19: IS | B19: Income Statement — fully linked to schedules
A20: BS | B20: Balance Sheet — links to IS, CF, WC, and D&A
A21: CF | B21: Cash Flow Statement — indirect method, 3-way linked
A22: Checks | B22: Error flags — Balance Sheet balance test & CF reconciliation
A23: Dashboard | B23: Executive summary KPIs and key metrics
A25: ⚠️ INSTRUCTIONS
A26: 1. Only edit BLUE cells — these are hardcoded assumptions.
A27: 2. BLACK cells are formulas — do not overwrite.
A28: 3. GREEN cells pull data from other sheets — do not edit.
A29: 4. All figures in USD Millions (e.g., 391,035 = $391B).
A30: 5. If Balance Sheet does not balance, check the Checks tab first.

Sheet Assumptions
A1: APPLE INC. — MODEL ASSUMPTIONS
A2: All blue cells are hardcoded inputs. Formulas reference these cells across the model.
A3: Units | B3: Notes | C3: FY2022A | D3: FY2023A | E3: FY2024A | F3: FY2025E | G3: FY2026E
A4: A. REVENUE DRIVERS
A5: Total Revenue ($M) | B5: Actual/Projected | C5: 394328 | D5: 383285 | E5: 391035 | F5: =E5*(1+F6) -> 416061.24 | G5: =F5*(1+G6) -> 445185.53
A6: Revenue Growth (YoY %) | B6: % change | C6: historical | D6: -0.028 | E6: 0.0202 | F6: 0.064 | G6: 0.07
A7: Gross Margin % | B7: % of Revenue | C7: 0.4331 | D7: 0.4413 | E7: 0.4621 | F7: 0.4691 | G7: 0.475
A8: → COGS ($M) | B8: Derived | C8: =C5*(1-C7) -> 223544.54 | D8: =D5*(1-D7) -> 214141.33 | E8: =E5*(1-E7) -> 210337.73 | F8: =F5*(1-F7) -> 220886.91 | G8: =G5*(1-G7) -> 233722.4
A9: B. OPERATING EXPENSES
A10: R&D as % of Revenue | B10: % of Revenue | C10: 0.0666 | D10: 0.0781 | E10: 0.0802 | F10: 0.083 | G10: 0.083
A11: → R&D Expense ($M) | B11: Derived | C11: =C5*C10 -> 26262.245 | D11: =D5*D10 -> 29934.558 | E11: =E5*E10 -> 31361.007 | F11: =F5*F10 -> 34533.083 | G11: =G5*G10 -> 36950.399
A12: SG&A as % of Revenue | B12: % of Revenue | C12: 0.0636 | D12: 0.065 | E12: 0.0668 | F12: 0.066 | G12: 0.065
A13: → SG&A Expense ($M) | B13: Derived | C13: =C5*C12 -> 25079.261 | D13: =D5*D12 -> 24913.525 | E13: =E5*E12 -> 26121.138 | F13: =F5*F12 -> 27460.042 | G13: =G5*G12 -> 28937.059
A14: C. TAX & INTEREST
A15: Effective Tax Rate | B15: % of Pre-tax Income | C15: 0.162 | D15: 0.147 | E15: 0.241 | F15: 0.16 | G15: 0.16
A16: Interest / Other Income ($M) | B16: Net | C16: -334 | D16: -565 | E16: 269 | F16: -300 | G16: -250
A17: D. CAPEX & DEPRECIATION
A18: CapEx ($M) | B18: Cash outflow | C18: 10708 | D18: 10959 | E18: 9447 | F18: 9776 | G18: 10075
A19: Depreciation & Amortisation ($M) | B19: Non-cash charge | C19: 11104 | D19: 11519 | E19: 11445 | F19: 11700 | G19: 12000
A20: E. WORKING CAPITAL DAYS
A21: Days Sales Outstanding (DSO) | B21: AR days | C21: 26 | D21: 28 | E21: 31 | F21: 31 | G21: 31
A22: Days Inventory Outstanding (DIO) | B22: Inventory days | C22: 8 | D22: 11 | E22: 13 | F22: 13 | G22: 12
A23: Days Payable Outstanding (DPO) | B23: AP days | C23: 105 | D23: 107 | E23: 120 | F23: 118 | G23: 115
A24: F. DEBT & DIVIDENDS
A25: Total Debt - Beginning of Year ($M) | B25: Hardcoded | C25: 120069 | D25: 120069 | E25: 111088 | F25: 106629 | G25: 103629
A26: Net Debt Issuance / (Repayment) ($M) | B26: Net | C26: 150 | D26: -5923 | E26: 318 | F26: -3000 | G26: -3000
A27: Dividends Paid ($M) | B27: Cash outflow | C27: 14841 | D27: 15025 | E27: 15234 | F27: 15500 | G27: 15800
A28: Share Buybacks ($M) | B28: Cash outflow | C28: 89402 | D28: 77550 | E28: 94949 | F28: 85000 | G28: 80000

Sheet Revenue
A1: APPLE INC. — REVENUE SCHEDULE ($M)
A2: Revenue Segment | B2: Units | C2: FY2022A | D2: FY2023A | E2: FY2024A | F2: FY2025E | G2: FY2026E
A3: iPhone | B3: $M | C3: 205489 | D3: 200583 | E3: 201183 | F3: 213000 | G3: 224000
A4: Mac | B4: $M | C4: 40177 | D4: 29357 | E4: 30670 | F4: 32000 | G4: 33500
A5: iPad | B5: $M | C5: 29292 | D5: 28300 | E5: 26694 | F5: 28000 | G5: 29000
A6: Wearables/Home/Acc | B6: $M | C6: 41241 | D6: 39845 | E6: 37005 | F6: 38500 | G6: 40000
A7: Services | B7: $M | C7: 78129 | D7: 85200 | E7: 96169 | F7: 105000 | G7: 113000
A8: Total Revenue | C8: =SUM(C3:C7) -> 394328 | D8: =SUM(D3:D7) -> 383285 | E8: =SUM(E3:E7) -> 391721 | F8: =SUM(F3:F7) -> 416500 | G8: =SUM(G3:G7) -> 439500
A9: Revenue Growth (YoY %) | B9: % | C9: — | D9: =(D8-C8)/C8 -> -0.028004605 | E9: =(E8-D8)/D8 -> 0.022009732 | F9: =(F8-E8)/E8 -> 0.063256757 | G9: =(G8-F8)/F8 -> 0.055222089
A10: Revenue Mix %
A11: iPhone | C11: =C3/C8 -> 0.52111187 | D11: =D3/D8 -> 0.52332598 | E11: =E3/E8 -> 0.51358748 | F11: =F3/F8 -> 0.51140456 | G11: =G3/G8 -> 0.50967008
A12: Mac | C12: =C4/C8 -> 0.10188726 | D12: =D4/D8 -> 0.076593136 | E12: =E4/E8 -> 0.078295522 | F12: =F4/F8 -> 0.076830732 | G12: =G4/G8 -> 0.076222981
A13: iPad | C13: =C5/C8 -> 0.074283338 | D13: =D5/D8 -> 0.073835397 | E13: =E5/E8 -> 0.06814544 | F13: =F5/F8 -> 0.067226891 | G13: =G5/G8 -> 0.065984073
A14: Wearables/Home/Acc | C14: =C6/C8 -> 0.10458552 | D14: =D6/D8 -> 0.10395659 | E14: =E6/E8 -> 0.094467746 | F14: =F6/F8 -> 0.092436975 | G14: =G6/G8 -> 0.091012514
A15: Services | C15: =C7/C8 -> 0.19813201 | D15: =D7/D8 -> 0.2222889 | E15: =E7/E8 -> 0.24550382 | F15: =F7/F8 -> 0.25210084 | G15: =G7/G8 -> 0.25711035
A17: Source: Apple Inc. 10-K FY2022, FY2023, FY2024 (SEC EDGAR). FY2025E/FY2026E: analyst consensus.

Sheet Costs
A1: APPLE INC. — COST SCHEDULE ($M)
A2: Cost Item | B2: Units | C2: FY2022A | D2: FY2023A | E2: FY2024A | F2: FY2025E | G2: FY2026E
A3: COST OF REVENUE (COGS)
A4: COGS ($M) | B4: Derived | C4: =Assumptions!C8 -> 223544.54 | D4: =Assumptions!D8 -> 214141.33 | E4: =Assumptions!E8 -> 210337.73 | F4: =Assumptions!F8 -> 220886.91 | G4: =Assumptions!G8 -> 233722.4
A5: Gross Margin % | B5: % | C5: =Assumptions!C7 -> 0.4331 | D5: =Assumptions!D7 -> 0.4413 | E5: =Assumptions!E7 -> 0.4621 | F5: =Assumptions!F7 -> 0.4691 | G5: =Assumptions!G7 -> 0.475
A6: OPERATING EXPENSES
A7: Research & Development ($M) | B7: Derived | C7: =Assumptions!C11 -> 26262.245 | D7: =Assumptions!D11 -> 29934.558 | E7: =Assumptions!E11 -> 31361.007 | F7: =Assumptions!F11 -> 34533.083 | G7: =Assumptions!G11 -> 36950.399
A8: Selling, General & Administrative ($M) | B8: Derived | C8: =Assumptions!C13 -> 25079.261 | D8: =Assumptions!D13 -> 24913.525 | E8: =Assumptions!E13 -> 26121.138 | F8: =Assumptions!F13 -> 27460.042 | G8: =Assumptions!G13 -> 28937.059
A9: Total OpEx ($M) | C9: =C7+C8 -> 51341.506 | D9: =D7+D8 -> 54848.084 | E9: =E7+E8 -> 57482.145 | F9: =F7+F8 -> 61993.125 | G9: =G7+G8 -> 65887.458
A10: OpEx as % of Revenue | B10: % | C10: =C9/Revenue!C8 -> 0.1302 | D10: =D9/Revenue!D8 -> 0.1431 | E10: =E9/Revenue!E8 -> 0.14674257 | F10: =F9/Revenue!F8 -> 0.14884304 | G10: =G9/Revenue!G8 -> 0.14991458
A11: R&D as % of Revenue | B11: % | C11: =Assumptions!C10 -> 0.0666 | D11: =Assumptions!D10 -> 0.0781 | E11: =Assumptions!E10 -> 0.0802 | F11: =Assumptions!F10 -> 0.083 | G11: =Assumptions!G10 -> 0.083
A12: SG&A as % of Revenue | B12: % | C12: =Assumptions!C12 -> 0.0636 | D12: =Assumptions!D12 -> 0.065 | E12: =Assumptions!E12 -> 0.0668 | F12: =Assumptions!F12 -> 0.066 | G12: =Assumptions!G12 -> 0.065

Sheet Depreciation
A1: APPLE INC. — PP&E ROLL-FORWARD & DEPRECIATION ($M)
A2: PP&E Schedule | B2: Units | C2: FY2022A | D2: FY2023A | E2: FY2024A | F2: FY2025E | G2: FY2026E
A3: Opening PP&E (Gross, Net), $M | B3: $M | C3: 39440 | D3: 42117 | E3: 43715 | F3: =E7 -> 41717 | G3: =F7 -> 39793
A4: Add: Capital Expenditures ($M) | B4: $M | C4: =Assumptions!C18 -> 10708 | D4: =Assumptions!D18 -> 10959 | E4: =Assumptions!E18 -> 9447 | F4: =Assumptions!F18 -> 9776 | G4: =Assumptions!G18 -> 10075
A5: Less: Depreciation & Amortisation ($M) | B5: $M | C5: =Assumptions!C19 -> 11104 | D5: =Assumptions!D19 -> 11519 | E5: =Assumptions!E19 -> 11445 | F5: =Assumptions!F19 -> 11700 | G5: =Assumptions!G19 -> 12000
A6: Less: Disposals / Other ($M) | B6: $M | C6: 427 | D6: 1921 | E6: 0 | F6: 0 | G6: 0
A7: Closing PP&E (Net) $M | B7: $M | C7: =C3+C4-C5-C6 -> 38617 | D7: =D3+D4-D5-D6 -> 39636 | E7: =E3+E4-E5-E6 -> 41717 | F7: =F3+F4-F5-F6 -> 39793 | G7: =G3+G4-G5-G6 -> 37868
A8: D&A as % of Opening PP&E | B8: % | C8: =C5/C3 -> 0.28154158 | D8: =D5/D3 -> 0.27350001 | E8: =E5/E3 -> 0.26180945 | F8: =F5/F3 -> 0.2804612 | G8: =G5/G3 -> 0.30156058
A9: CapEx as % of Revenue | B9: % | C9: =C4/Revenue!C8 -> 0.027155059 | D9: =D4/Revenue!D8 -> 0.028592301 | E9: =E4/Revenue!E8 -> 0.024116654 | F9: =F4/Revenue!F8 -> 0.023471789 | G9: =G4/Revenue!G8 -> 0.022923777
A11: Formula Logic: Closing PP&E = Opening + CapEx – D&A – Disposals

Sheet Working Capital
A1: APPLE INC. — WORKING CAPITAL SCHEDULE ($M)
A2: Working Capital Item | B2: Units | C2: FY2022A | D2: FY2023A | E2: FY2024A | F2: FY2025E | G2: FY2026E
A3: Days Sales Outstanding (DSO) | B3: Days | C3: =Assumptions!C21 -> 26 | D3: =Assumptions!D21 -> 28 | E3: =Assumptions!E21 -> 31 | F3: =Assumptions!F21 -> 31 | G3: =Assumptions!G21 -> 31
A4: Accounts Receivable ($M) | B4: $M | C4: =ROUND(C3*Revenue!C8/365,0) -> 28089 | D4: =ROUND(D3*Revenue!D8/365,0) -> 29403 | E4: =ROUND(E3*Revenue!E8/365,0) -> 33269 | F4: =ROUND(F3*Revenue!F8/365,0) -> 35374 | G4: =ROUND(G3*Revenue!G8/365,0) -> 37327
A5: Days Inventory Outstanding (DIO) | B5: Days | C5: =Assumptions!C22 -> 8 | D5: =Assumptions!D22 -> 11 | E5: =Assumptions!E22 -> 13 | F5: =Assumptions!F22 -> 13 | G5: =Assumptions!G22 -> 12
A6: Inventories ($M) | B6: $M | C6: =ROUND(C5*Costs!C4/365,0) -> 4900 | D6: =ROUND(D5*Costs!D4/365,0) -> 6454 | E6: =ROUND(E5*Costs!E4/365,0) -> 7491 | F6: =ROUND(F5*Costs!F4/365,0) -> 7867 | G6: =ROUND(G5*Costs!G4/365,0) -> 7684
A7: Days Payable Outstanding (DPO) | B7: Days | C7: =Assumptions!C23 -> 105 | D7: =Assumptions!D23 -> 107 | E7: =Assumptions!E23 -> 120 | F7: =Assumptions!F23 -> 118 | G7: =Assumptions!G23 -> 115
A8: Accounts Payable ($M) | B8: $M | C8: =ROUND(C7*Costs!C4/365,0) -> 64307 | D8: =ROUND(D7*Costs!D4/365,0) -> 62776 | E8: =ROUND(E7*Costs!E4/365,0) -> 69152 | F8: =ROUND(F7*Costs!F4/365,0) -> 71410 | G8: =ROUND(G7*Costs!G4/365,0) -> 73639
A9: Net Working Capital ($M) | B9: AR+Inv-AP | C9: =C4+C6-C8 -> -31318 | D9: =D4+D6-D8 -> -26919 | E9: =E4+E6-E8 -> -28392 | F9: =F4+F6-F8 -> -28169 | G9: =G4+G6-G8 -> -28628
A10: Change in Working Capital ($M) | B10: YoY Δ | C10: — | D10: =-(D9-C9) -> -4399 | E10: =-(E9-D9) -> 1473 | F10: =-(F9-E9) -> -223 | G10: =-(G9-F9) -> 459
A12: Formula: AR = DSO × Revenue ÷ 365 | Inventory = DIO × COGS ÷ 365 | AP = DPO × COGS ÷ 365
A13: Change in WC = –(Closing NWC – Opening NWC) | Positive = cash inflow (WC decreased)

Sheet IS
A1: APPLE INC. — INCOME STATEMENT ($M)
A2: Line Item | B2: Units | C2: FY2022A | D2: FY2023A | E2: FY2024A | F2: FY2025E | G2: FY2026E
A3: Revenue | B3: $M | C3: =Revenue!C8 -> 394328 | D3: =Revenue!D8 -> 383285 | E3: =Revenue!E8 -> 391721 | F3: =Revenue!F8 -> 416500 | G3: =Revenue!G8 -> 439500
A4: Cost of Revenue (COGS) | B4: $M | C4: =Costs!C4 -> 223544.54 | D4: =Costs!D4 -> 214141.33 | E4: =Costs!E4 -> 210337.73 | F4: =Costs!F4 -> 220886.91 | G4: =Costs!G4 -> 233722.4
A5: Gross Profit | B5: $M | C5: =C3-C4 -> 170783.46 | D5: =D3-D4 -> 169143.67 | E5: =E3-E4 -> 181383.27 | F5: =F3-F4 -> 195613.09 | G5: =G3-G4 -> 205777.6
A6: Gross Margin % | B6: $M | C6: =C5/C3 -> 0.4331 | D6: =D5/D3 -> 0.4413 | E6: =E5/E3 -> 0.463042 | F6: =F5/F3 -> 0.46965927 | G6: =G5/G3 -> 0.46820842
A7: Operating Expenses
A8: Research & Development | B8: $M | C8: =Costs!C7 -> 26262.245 | D8: =Costs!D7 -> 29934.558 | E8: =Costs!E7 -> 31361.007 | F8: =Costs!F7 -> 34533.083 | G8: =Costs!G7 -> 36950.399
A9: Selling, General & Administrative | B9: $M | C9: =Costs!C8 -> 25079.261 | D9: =Costs!D8 -> 24913.525 | E9: =Costs!E8 -> 26121.138 | F9: =Costs!F8 -> 27460.042 | G9: =Costs!G8 -> 28937.059
A10: Total Operating Expenses | B10: $M | C10: =C8+C9 -> 51341.506 | D10: =D8+D9 -> 54848.084 | E10: =E8+E9 -> 57482.145 | F10: =F8+F9 -> 61993.125 | G10: =G8+G9 -> 65887.458
A11: EBITDA | B11: $M | C11: =C5-C10+Assumptions!C19 -> 130545.95 | D11: =D5-D10+Assumptions!D19 -> 125814.59 | E11: =E5-E10+Assumptions!E19 -> 135346.13 | F11: =F5-F10+Assumptions!F19 -> 145319.96 | G11: =G5-G10+Assumptions!G19 -> 151890.14
A12: EBITDA Margin % | B12: $M | C12: =C11/C3 -> 0.3310593 | D12: =D11/D3 -> 0.32825335 | E12: =E11/E3 -> 0.34551665 | F12: =F11/F3 -> 0.34890747 | G12: =G11/G3 -> 0.34559759
A13: Less: Depreciation & Amortisation | B13: $M | C13: =Assumptions!C19 -> 11104 | D13: =Assumptions!D19 -> 11519 | E13: =Assumptions!E19 -> 11445 | F13: =Assumptions!F19 -> 11700 | G13: =Assumptions!G19 -> 12000
A14: EBIT (Operating Income) | B14: $M | C14: =C11-C13 -> 119441.95 | D14: =D11-D13 -> 114295.59 | E14: =E11-E13 -> 123901.13 | F14: =F11-F13 -> 133619.96 | G14: =G11-G13 -> 139890.14
A15: EBIT Margin % | B15: $M | C15: =C14/C3 -> 0.3029 | D15: =D14/D3 -> 0.2982 | E15: =E14/E3 -> 0.31629943 | F15: =F14/F3 -> 0.32081624 | G15: =G14/G3 -> 0.31829383
A16: Interest / Other Income (Expense) | B16: $M | C16: =Assumptions!C16 -> -334 | D16: =Assumptions!D16 -> -565 | E16: =Assumptions!E16 -> 269 | F16: =Assumptions!F16 -> -300 | G16: =Assumptions!G16 -> -250
A17: Pre-Tax Income | B17: $M | C17: =C14+C16 -> 119107.95 | D17: =D14+D16 -> 113730.59 | E17: =E14+E16 -> 124170.13 | F17: =F14+F16 -> 133319.96 | G17: =G14+G16 -> 139640.14
A18: Income Tax Expense | B18: $M | C18: =IF(C17>0,C17*Assumptions!C15,0) -> 19295.488 | D18: =IF(D17>0,D17*Assumptions!D15,0) -> 16718.396 | E18: =IF(E17>0,E17*Assumptions!E15,0) -> 29925.001 | F18: =IF(F17>0,F17*Assumptions!F15,0) -> 21331.194 | G18: =IF(G17>0,G17*Assumptions!G15,0) -> 22342.422
A19: NET INCOME | B19: $M | C19: =C17-C18 -> 99812.463 | D19: =D17-D18 -> 97012.191 | E19: =E17-E18 -> 94245.128 | F19: =F17-F18 -> 111988.77 | G19: =G17-G18 -> 117297.72
A20: Net Margin % | B20: $M | C20: =C19/C3 -> 0.25312041 | D20: =D19/D3 -> 0.25310719 | E20: =E19/E3 -> 0.24059248 | F20: =F19/F3 -> 0.2688806 | G20: =G19/G3 -> 0.26688901
A21: Effective Tax Rate (Check) | B21: $M | C21: =IF(C17>0,C18/C17,0) -> 0.162 | D21: =IF(D17>0,D18/D17,0) -> 0.147 | E21: =IF(E17>0,E18/E17,0) -> 0.241 | F21: =IF(F17>0,F18/F17,0) -> 0.16 | G21: =IF(G17>0,G18/G17,0) -> 0.16

Sheet BS
A1: APPLE INC. — BALANCE SHEET ($M)
A2: Balance Sheet Item | B2: Units | C2: FY2022A | D2: FY2023A | E2: FY2024A | F2: FY2025E | G2: FY2026E
A3: ASSETS
A4: Current Assets
A5: Cash & Cash Equivalents | B5: $M | C5: 23646 | D5: 29965 | E5: 29943 | F5: =E5+CF!F21 -> 70075.769 | G5: =F5+CF!G21 -> 161033.26
A6: Accounts Receivable | B6: $M | C6: ='Working Capital'!C4 -> 28089 | D6: ='Working Capital'!D4 -> 29403 | E6: ='Working Capital'!E4 -> 33269 | F6: ='Working Capital'!F4 -> 35374 | G6: ='Working Capital'!G4 -> 37327
A7: Inventories | B7: $M | C7: ='Working Capital'!C6 -> 4900 | D7: ='Working Capital'!D6 -> 6454 | E7: ='Working Capital'!E6 -> 7491 | F7: ='Working Capital'!F6 -> 7867 | G7: ='Working Capital'!G6 -> 7684
A8: Marketable Securities (ST) | B8: $M | C8: 24658 | D8: 31590 | E8: 35228 | F8: 36000 | G8: 37000
A9: Other Current Assets | B9: $M | C9: 21223 | D9: 14695 | E9: 14287 | F9: 14000 | G9: 13800
A10: Total Current Assets | B10: $M | C10: =SUM(C5:C9) -> 102516 | D10: =SUM(D5:D9) -> 112107 | E10: =SUM(E5:E9) -> 120218 | F10: =SUM(F5:F9) -> 163316.77 | G10: =SUM(G5:G9) -> 256844.26
A11: Non-Current Assets
A12: PP&E, Net | B12: $M | C12: =Depreciation!C7 -> 38617 | D12: =Depreciation!D7 -> 39636 | E12: =Depreciation!E7 -> 41717 | F12: =Depreciation!F7 -> 39793 | G12: =Depreciation!G7 -> 37868
A13: Marketable Securities (LT) | B13: $M | C13: 120805 | D13: 100544 | E13: 91479 | F13: 88000 | G13: 84000
A14: Other Non-Current Assets | B14: $M | C14: 54428 | D14: 64758 | E14: 74834 | F14: 76000 | G14: 78000
A15: Total Non-Current Assets | B15: $M | C15: =SUM(C12:C14) -> 213850 | D15: =SUM(D12:D14) -> 204938 | E15: =SUM(E12:E14) -> 208030 | F15: =SUM(F12:F14) -> 203793 | G15: =SUM(G12:G14) -> 199868
A16: TOTAL ASSETS | B16: $M | C16: =C10+C15 -> 316366 | D16: =D10+D15 -> 317045 | E16: =E10+E15 -> 328248 | F16: =F10+F15 -> 367109.77 | G16: =G10+G15 -> 456712.26
A17: LIABILITIES & EQUITY
A18: Current Liabilities
A19: Accounts Payable | B19: $M | C19: ='Working Capital'!C8 -> 64307 | D19: ='Working Capital'!D8 -> 62776 | E19: ='Working Capital'!E8 -> 69152 | F19: ='Working Capital'!F8 -> 71410 | G19: ='Working Capital'!G8 -> 73639
A20: Short-Term Debt / Commercial Paper | B20: $M | C20: 21110 | D20: 15807 | E20: 20879 | F20: 18000 | G20: 16000
A21: Deferred Revenue (ST) | B21: $M | C21: 7912 | D21: 8061 | E21: 8249 | F21: 8500 | G21: 8700
A22: Other Current Liabilities | B22: $M | C22: 60845 | D22: 58563 | E22: 78304 | F22: 75000 | G22: 72000
A23: Total Current Liabilities | B23: $M | C23: =SUM(C19:C22) -> 154174 | D23: =SUM(D19:D22) -> 145207 | E23: =SUM(E19:E22) -> 176584 | F23: =SUM(F19:F22) -> 172910 | G23: =SUM(G19:G22) -> 170339
A24: Non-Current Liabilities
A25: Long-Term Debt | B25: $M | C25: 98959 | D25: 95281 | E25: 85750 | F25: 82000 | G25: 79000
A26: Other Non-Current Liabilities | B26: $M | C26: 49142 | D26: 49848 | E26: 45888 | F26: 44000 | G26: 43000
A27: Total Non-Current Liabilities | B27: $M | C27: =C25+C26 -> 148101 | D27: =D25+D26 -> 145129 | E27: =E25+E26 -> 131638 | F27: =F25+F26 -> 126000 | G27: =G25+G26 -> 122000
A28: Total Liabilities | B28: $M | C28: =C23+C27 -> 302275 | D28: =D23+D27 -> 290336 | E28: =E23+E27 -> 308222 | F28: =F23+F27 -> 298910 | G28: =G23+G27 -> 292339
A29: Shareholders' Equity
A30: Common Stock & APIC | B30: $M | C30: 64849 | D30: 73812 | E30: 83276 | F30: 88000 | G30: 92000
A31: Retained Earnings (Deficit) | B31: $M | C31: -3068 | D31: -214 | E31: -19154 | F31: =E31+IS!F19-Assumptions!F27-Assumptions!F28 -> -7665.2311 | G31: =F31+IS!G19-Assumptions!G27-Assumptions!G28 -> 13832.487
A32: Accumulated OCI | B32: $M | C32: -11109 | D32: -11452 | E32: -7172 | F32: -7000 | G32: -6800
A33: Total Shareholders' Equity | B33: $M | C33: =C30+C31+C32 -> 50672 | D33: =D30+D31+D32 -> 62146 | E33: =E30+E31+E32 -> 56950 | F33: =F30+F31+F32 -> 73334.769 | G33: =G30+G31+G32 -> 99032.487
A34: TOTAL LIABILITIES + EQUITY | B34: $M | C34: =C28+C33 -> 352947 | D34: =D28+D33 -> 352482 | E34: =E28+E33 -> 365172 | F34: =F28+F33 -> 372244.77 | G34: =G28+G33 -> 391371.49
A35: ✅ BS CHECK (Assets – Liabilities – Equity = 0) | B35: Must=0 | C35: =C16-C34 -> -36581 | D35: =D16-D34 -> -35437 | E35: =E16-E34 -> -36924 | F35: =F16-F34 -> -5135 | G35: =G16-G34 -> 65340.769

Sheet CF
A1: APPLE INC. — CASH FLOW STATEMENT ($M) — INDIRECT METHOD
A2: Cash Flow Item | B2: Units | C2: FY2022A | D2: FY2023A | E2: FY2024A | F2: FY2025E | G2: FY2026E
A3: OPERATING ACTIVITIES
A4: Net Income | B4: $M | C4: =IS!C19 -> 99812.463 | D4: =IS!D19 -> 97012.191 | E4: =IS!E19 -> 94245.128 | F4: =IS!F19 -> 111988.77 | G4: =IS!G19 -> 117297.72
A5: Add: Depreciation & Amortisation | B5: $M | C5: =Assumptions!C19 -> 11104 | D5: =Assumptions!D19 -> 11519 | E5: =Assumptions!E19 -> 11445 | F5: =Assumptions!F19 -> 11700 | G5: =Assumptions!G19 -> 12000
A6: Change in Working Capital | B6: $M | C6: — | D6: ='Working Capital'!D10 -> -4399 | E6: ='Working Capital'!E10 -> 1473 | F6: ='Working Capital'!F10 -> -223 | G6: ='Working Capital'!G10 -> 459
A7: Other Operating Adjustments | B7: $M | C7: 2136 | D7: 62 | E7: 7339 | F7: 3000 | G7: 3000
A8: Cash From Operating Activities | B8: $M | C8: =SUM(C4:C7) -> 113052.46 | D8: =SUM(D4:D7) -> 104194.19 | E8: =SUM(E4:E7) -> 114502.13 | F8: =SUM(F4:F7) -> 126465.77 | G8: =SUM(G4:G7) -> 132756.72
A9: INVESTING ACTIVITIES
A10: Capital Expenditures (CapEx) | B10: $M | C10: =-Assumptions!C18 -> -10708 | D10: =-Assumptions!D18 -> -10959 | E10: =-Assumptions!E18 -> -9447 | F10: =-Assumptions!F18 -> -9776 | G10: =-Assumptions!G18 -> -10075
A11: Acquisitions & Other Investing | B11: $M | C11: -11646 | D11: 7164 | E11: -6413 | F11: -3000 | G11: -3000
A12: Cash From Investing Activities | B12: $M | C12: =C10+C11 -> -22354 | D12: =D10+D11 -> -3795 | E12: =E10+E11 -> -15860 | F12: =F10+F11 -> -12776 | G12: =G10+G11 -> -13075
A13: FINANCING ACTIVITIES
A14: Net Debt Issuance / (Repayment) | B14: $M | C14: =Assumptions!C26 -> 150 | D14: =Assumptions!D26 -> -5923 | E14: =Assumptions!E26 -> 318 | F14: =Assumptions!F26 -> -3000 | G14: =Assumptions!G26 -> -3000
A15: Dividends Paid | B15: $M | C15: =-Assumptions!C27 -> -14841 | D15: =-Assumptions!D27 -> -15025 | E15: =-Assumptions!E27 -> -15234 | F15: =-Assumptions!F27 -> -15500 | G15: =-Assumptions!G27 -> -15800
A16: Share Buybacks | B16: $M | C16: =-Assumptions!C28 -> -89402 | D16: =-Assumptions!D28 -> -77550 | E16: =-Assumptions!E28 -> -94949 | F16: =-Assumptions!F28 -> -85000 | G16: =-Assumptions!G28 -> -80000
A17: Cash From Financing Activities | B17: $M | C17: =C14+C15+C16 -> -104093 | D17: =D14+D15+D16 -> -98498 | E17: =E14+E15+E16 -> -109865 | F17: =F14+F15+F16 -> -103500 | G17: =G14+G15+G16 -> -98800
A18: FX / Other Impact on Cash | B18: $M | C18: 0 | D18: 0 | E18: 0 | F18: 0 | G18: 0
A19: Beginning Cash Balance | B19: $M | C19: 34940 | D19: 23646 | E19: 29965 | F19: =BS!E5 -> 29943 | G19: =BS!F5 -> 70075.769
A20: Net Change in Cash | B20: $M | C20: =C8+C12+C17+C18 -> -13394.537 | D20: =D8+D12+D17+D18 -> 1901.1907 | E20: =E8+E12+E17+E18 -> -11222.872 | F20: =F8+F12+F17+F18 -> 10189.769 | G20: =G8+G12+G17+G18 -> 20881.718
A21: Ending Cash Balance | B21: $M | C21: =C19+C20 -> 21545.463 | D21: =D19+D20 -> 25547.191 | E21: =E19+E20 -> 18742.128 | F21: =F19+F20 -> 40132.769 | G21: =G19+G20 -> 90957.487
A22: Free Cash Flow (OCF – CapEx) | B22: $M | C22: =C8+C10 -> 102344.46 | D22: =D8+D10 -> 93235.191 | E22: =E8+E10 -> 105055.13 | F22: =F8+F10 -> 116689.77 | G22: =G8+G10 -> 122681.72
A23: FCF Margin % | B23: % | C23: =C22/IS!C3 -> 0.25954146 | D23: =D22/IS!D3 -> 0.24325291 | E23: =E22/IS!E3 -> 0.26818865 | F23: =F22/IS!F3 -> 0.28016751 | G23: =G22/IS!G3 -> 0.27913929

Sheet Checks
A1: MODEL INTEGRITY CHECKS & ERROR FLAGS
A2: Check | B2: Result | C2: FY2022A | D2: FY2023A | E2: FY2024A | F2: FY2025E | G2: FY2026E
A3: If any cell below shows ERROR — your model has a problem. All checks must show ✅ OK
A4: 1. BALANCE SHEET CHECK (Assets = Liabilities + Equity)
A5: Total Assets ($M) | B5: $M | C5: =BS!C16 -> 316366 | D5: =BS!D16 -> 317045 | E5: =BS!E16 -> 328248 | F5: =BS!F16 -> 367109.77 | G5: =BS!G16 -> 456712.26
A6: Total Liabilities + Equity ($M) | B6: $M | C6: =BS!C34 -> 352947 | D6: =BS!D34 -> 352482 | E6: =BS!E34 -> 365172 | F6: =BS!F34 -> 372244.77 | G6: =BS!G34 -> 391371.49
A7: Difference (Must = 0) | B7: Must=0 | C7: =C5-C6 -> -36581 | D7: =D5-D6 -> -35437 | E7: =E5-E6 -> -36924 | F7: =F5-F6 -> -5135 | G7: =G5-G6 -> 65340.769
A8: ⚡ Balance Sheet Status | B8: Flag | C8: =IF(ABS(C7)<0.01,"✅ OK","❌ ERROR — BS does not balance") -> ❌ ERROR — BS does not balance | D8: =IF(ABS(D7)<0.01,"✅ OK","❌ ERROR — BS does not balance") -> ❌ ERROR — BS does not balance | E8: =IF(ABS(E7)<0.01,"✅ OK","❌ ERROR — BS does not balance") -> ❌ ERROR — BS does not balance | F8: =IF(ABS(F7)<0.01,"✅ OK","❌ ERROR — BS does not balance") -> ❌ ERROR — BS does not balance | G8: =IF(ABS(G7)<0.01,"✅ OK","❌ ERROR — BS does not balance") -> ❌ ERROR — BS does not balance
A9: 2. CASH FLOW RECONCILIATION CHECK
A10: Ending Cash per Cash Flow Statement | B10: $M | C10: =CF!C21 -> 21545.463 | D10: =CF!D21 -> 25547.191 | E10: =CF!E21 -> 18742.128 | F10: =CF!F21 -> 40132.769 | G10: =CF!G21 -> 90957.487
A11: Cash per Balance Sheet | B11: $M | C11: =BS!C5 -> 23646 | D11: =BS!D5 -> 29965 | E11: =BS!E5 -> 29943 | F11: =BS!F5 -> 70075.769 | G11: =BS!G5 -> 161033.26
A12: Difference (Must = 0) | B12: Must=0 | C12: =C10-C11 -> -2100.5369 | D12: =D10-D11 -> -4417.8093 | E12: =E10-E11 -> -11200.872 | F12: =F10-F11 -> -29943 | G12: =G10-G11 -> -70075.769
A13: ⚡ Cash Reconciliation Status | B13: Flag | C13: =IF(ABS(C12)<1,"✅ OK","❌ ERROR — Cash does not reconcile") -> ❌ ERROR — Cash does not reconcile | D13: =IF(ABS(D12)<1,"✅ OK","❌ ERROR — Cash does not reconcile") -> ❌ ERROR — Cash does not reconcile | E13: =IF(ABS(E12)<1,"✅ OK","❌ ERROR — Cash does not reconcile") -> ❌ ERROR — Cash does not reconcile | F13: =IF(ABS(F12)<1,"✅ OK","❌ ERROR — Cash does not reconcile") -> ❌ ERROR — Cash does not reconcile | G13: =IF(ABS(G12)<1,"✅ OK","❌ ERROR — Cash does not reconcile") -> ❌ ERROR — Cash does not reconcile
A14: 3. PROFITABILITY SANITY CHECKS
A15: Gross Margin % (expect 43–49%) | B15: % | C15: =IS!C6 -> 0.4331 | D15: =IS!D6 -> 0.4413 | E15: =IS!E6 -> 0.463042 | F15: =IS!F6 -> 0.46965927 | G15: =IS!G6 -> 0.46820842
A16: EBITDA Margin % (expect 32–36%) | B16: % | C16: =IS!C12 -> 0.3310593 | D16: =IS!D12 -> 0.32825335 | E16: =IS!E12 -> 0.34551665 | F16: =IS!F12 -> 0.34890747 | G16: =IS!G12 -> 0.34559759
A17: Net Margin % (expect 22–28%) | B17: % | C17: =IS!C20 -> 0.25312041 | D17: =IS!D20 -> 0.25310719 | E17: =IS!E20 -> 0.24059248 | F17: =IS!F20 -> 0.2688806 | G17: =IS!G20 -> 0.26688901
A18: FCF Margin % (expect 23–30%) | B18: % | C18: =CF!C23 -> 0.25954146 | D18: =CF!D23 -> 0.24325291 | E18: =CF!E23 -> 0.26818865 | F18: =CF!F23 -> 0.28016751 | G18: =CF!G23 -> 0.27913929
A19: 4. OVERALL MODEL STATUS
A20: ⚡ ALL CHECKS PASSED? | B20: Summary | C20: =IF(AND(C8="✅ OK",C13="✅ OK"),"✅ MODEL IS CLEAN","❌ ERRORS EXIST — SEE ABOVE") -> ❌ ERRORS EXIST — SEE ABOVE

Sheet Dashboard
A1: APPLE INC. (AAPL) — EXECUTIVE SUMMARY DASHBOARD
A2: Figures in USD Millions ($M) | FY ends September | Source: Apple 10-K + Analyst Estimates
A3: KPI | B3: Units | C3: FY2022A | D3: FY2023A | E3: FY2024A | F3: FY2025E | G3: FY2026E
A4: ── INCOME STATEMENT ──
A5: Revenue | B5: $M | C5: =IS!C3 -> 394328 | D5: =IS!D3 -> 383285 | E5: =IS!E3 -> 391721 | F5: =IS!F3 -> 416500 | G5: =IS!G3 -> 439500
A6: Revenue Growth % | B6: % | C6: — | D6: =Revenue!D9 -> -0.028004605 | E6: =Revenue!E9 -> 0.022009732 | F6: =Revenue!F9 -> 0.063256757 | G6: =Revenue!G9 -> 0.055222089
A7: Gross Profit | B7: $M | C7: =IS!C5 -> 170783.46 | D7: =IS!D5 -> 169143.67 | E7: =IS!E5 -> 181383.27 | F7: =IS!F5 -> 195613.09 | G7: =IS!G5 -> 205777.6
A8: Gross Margin % | B8: % | C8: =IS!C6 -> 0.4331 | D8: =IS!D6 -> 0.4413 | E8: =IS!E6 -> 0.463042 | F8: =IS!F6 -> 0.46965927 | G8: =IS!G6 -> 0.46820842
A9: EBITDA | B9: $M | C9: =IS!C11 -> 130545.95 | D9: =IS!D11 -> 125814.59 | E9: =IS!E11 -> 135346.13 | F9: =IS!F11 -> 145319.96 | G9: =IS!G11 -> 151890.14
A10: EBITDA Margin % | B10: % | C10: =IS!C12 -> 0.3310593 | D10: =IS!D12 -> 0.32825335 | E10: =IS!E12 -> 0.34551665 | F10: =IS!F12 -> 0.34890747 | G10: =IS!G12 -> 0.34559759
A11: EBIT | B11: $M | C11: =IS!C14 -> 119441.95 | D11: =IS!D14 -> 114295.59 | E11: =IS!E14 -> 123901.13 | F11: =IS!F14 -> 133619.96 | G11: =IS!G14 -> 139890.14
A12: EBIT Margin % | B12: % | C12: =IS!C15 -> 0.3029 | D12: =IS!D15 -> 0.2982 | E12: =IS!E15 -> 0.31629943 | F12: =IS!F15 -> 0.32081624 | G12: =IS!G15 -> 0.31829383
A13: Net Income | B13: $M | C13: =IS!C19 -> 99812.463 | D13: =IS!D19 -> 97012.191 | E13: =IS!E19 -> 94245.128 | F13: =IS!F19 -> 111988.77 | G13: =IS!G19 -> 117297.72
A14: Net Margin % | B14: % | C14: =IS!C20 -> 0.25312041 | D14: =IS!D20 -> 0.25310719 | E14: =IS!E20 -> 0.24059248 | F14: =IS!F20 -> 0.2688806 | G14: =IS!G20 -> 0.26688901
A15: ── CASH FLOW ──
A16: Operating Cash Flow | B16: $M | C16: =CF!C8 -> 113052.46 | D16: =CF!D8 -> 104194.19 | E16: =CF!E8 -> 114502.13 | F16: =CF!F8 -> 126465.77 | G16: =CF!G8 -> 132756.72
A17: Capital Expenditures | B17: $M | C17: =Assumptions!C18 -> 10708 | D17: =Assumptions!D18 -> 10959 | E17: =Assumptions!E18 -> 9447 | F17: =Assumptions!F18 -> 9776 | G17: =Assumptions!G18 -> 10075
A18: Free Cash Flow | B18: $M | C18: =CF!C22 -> 102344.46 | D18: =CF!D22 -> 93235.191 | E18: =CF!E22 -> 105055.13 | F18: =CF!F22 -> 116689.77 | G18: =CF!G22 -> 122681.72
A19: FCF Margin % | B19: % | C19: =CF!C23 -> 0.25954146 | D19: =CF!D23 -> 0.24325291 | E19: =CF!E23 -> 0.26818865 | F19: =CF!F23 -> 0.28016751 | G19: =CF!G23 -> 0.27913929
A20: ── BALANCE SHEET ──
A21: Cash & Equivalents | B21: $M | C21: =BS!C5 -> 23646 | D21: =BS!D5 -> 29965 | E21: =BS!E5 -> 29943 | F21: =BS!F5 -> 70075.769 | G21: =BS!G5 -> 161033.26
A22: Total Assets | B22: $M | C22: =BS!C16 -> 316366 | D22: =BS!D16 -> 317045 | E22: =BS!E16 -> 328248 | F22: =BS!F16 -> 367109.77 | G22: =BS!G16 -> 456712.26
A23: Total Debt | B23: $M | C23: =BS!C20+BS!C25 -> 120069 | D23: =BS!D20+BS!D25 -> 111088 | E23: =BS!E20+BS!E25 -> 106629 | F23: =BS!F20+BS!F25 -> 100000 | G23: =BS!G20+BS!G25 -> 95000
A24: Total Equity | B24: $M | C24: =BS!C33 -> 50672 | D24: =BS!D33 -> 62146 | E24: =BS!E33 -> 56950 | F24: =BS!F33 -> 73334.769 | G24: =BS!G33 -> 99032.487
A26: Note: FY2025E and FY2026E are projections based on analyst consensus and trend extrapolation. Not financial advice.
